expetator/__init__.py
expetator/add_energy.py
expetator/bundle.py
expetator/clean_csv.py
expetator/demo_watermark.py
expetator/experiment.py
expetator/get_nb_freq.py
expetator/monitoring_csv.py
expetator/monitoring_list.py
expetator/remove_watermark.py
expetator/tools.py
expetator/watermark.py
expetator/benchmarks/__init__.py
expetator/benchmarks/cpu.c
expetator/benchmarks/cpubench.py
expetator/benchmarks/genericbench.py
expetator/benchmarks/gpucpubench.py
expetator/benchmarks/gpumembench.py
expetator/benchmarks/gromacsBFC.tpr
expetator/benchmarks/gromacsMEM.tpr
expetator/benchmarks/gromacsbench.py
expetator/benchmarks/m.cu
expetator/benchmarks/mem.c
expetator/benchmarks/membench.py
expetator/benchmarks/mpi_generic.c
expetator/benchmarks/mpibench.py
expetator/benchmarks/npbbench.py
expetator/benchmarks/percentage_load.c
expetator/benchmarks/percentagebench.py
expetator/benchmarks/sleepbench.py
expetator/benchmarks/watermark.c
expetator/benchmarks/watermark.py
expetator/benchmarks/genericbench/setcpulatency.c
expetator/benchmarks/genericbench/ub_cpu_alu.c
expetator/benchmarks/genericbench/ub_cpu_cu.c
expetator/benchmarks/genericbench/ub_cpu_rand.c
expetator/benchmarks/genericbench/ub_mem_access.c
expetator/benchmarks/genericbench/uc-generic.sh
expetator/leverages/README.md
expetator/leverages/__init__.py
expetator/leverages/dvfs.py
expetator/leverages/dvfs_pct.sh
expetator/leverages/gpuclock.py
expetator/leverages/gpupow.py
expetator/leverages/neosched.py
expetator/leverages/neosched_lib.h
expetator/leverages/neosched_main.c
expetator/leverages/neosched_mak
expetator/leverages/neosched_skel.c
expetator/leverages/nodeepsleep.py
expetator/leverages/pct.py
expetator/leverages/powercap.py
expetator/leverages/powercap.sh
expetator/leverages/template.py
expetator/monitors/__init__.py
expetator/monitors/kwollect.py
expetator/monitors/laptop_power_monitor.py
expetator/monitors/lperf.py
expetator/monitors/lperf_builtin-stat.diff
expetator/monitors/lperf_tools.tar.bz2
expetator-0.3.28.dist-info/licenses/LICENSE
expetator-0.3.28.dist-info/METADATA
expetator-0.3.28.dist-info/WHEEL
expetator-0.3.28.dist-info/entry_points.txt
expetator-0.3.28.dist-info/top_level.txt
expetator-0.3.28.dist-info/RECORD
