Metadata-Version: 2.4
Name: expetator
Version: 0.3.28
Summary: A framework for monitoring HPC applications using DVFS
Home-page: https://gitlab.irit.fr/sepia-pub/expetator
Author: Georges Da Costa
Author-email: georges.da-costa@irit.fr
Classifier: Programming Language :: Python :: 3
Classifier: License :: OSI Approved :: GNU General Public License v3 or later (GPLv3+)
Classifier: Operating System :: OS Independent
Requires-Python: >=3.6
License-File: LICENSE
Requires-Dist: execo
Requires-Dist: requests
Dynamic: author
Dynamic: author-email
Dynamic: classifier
Dynamic: description
Dynamic: description-content-type
Dynamic: home-page
Dynamic: license-file
Dynamic: requires-dist
Dynamic: requires-python
Dynamic: summary
